studentcodes/__init__.py
studentcodes/waps.py
studentcodes-0.1.1.dist-info/METADATA
studentcodes-0.1.1.dist-info/WHEEL
studentcodes-0.1.1.dist-info/top_level.txt
studentcodes-0.1.1.dist-info/RECORD
