Metadata-Version: 2.4
Name: studentcodes
Version: 0.1.1
Summary: A collection of beginner-friendly Python WAPs for copy-paste use
Home-page: https://example.com/studentcodes
Author: Student Code Team
Classifier: Programming Language :: Python :: 3
Classifier: Intended Audience :: Education
Classifier: License :: OSI Approved :: MIT License
Classifier: Operating System :: OS Independent
Requires-Python: >=3.6
